fast_explorer/__init__.py
fast_explorer/fast_explorer.py
fast_explorer-0.1.2.dist-info/LICENSE
fast_explorer-0.1.2.dist-info/METADATA
fast_explorer-0.1.2.dist-info/WHEEL
fast_explorer-0.1.2.dist-info/top_level.txt
fast_explorer-0.1.2.dist-info/RECORD
