Metadata-Version: 2.1
Name: fast-explorer
Version: 0.1.2
Summary: package to explore pandas data easily
Home-page: UNKNOWN
Author: Priyal Bankar
Author-email: bankarpriyal08@gmail.com
License: MIT
Keywords: pandas,data,anaysis
Platform: UNKNOWN
Classifier: Development Status :: 3 - Alpha
Classifier: Intended Audience :: Developers
Classifier: Topic :: Scientific/Engineering :: Mathematics
Classifier: License :: OSI Approved :: MIT License
Classifier: Programming Language :: Python :: 3.7
Requires-Dist: pandas
